awarecache/__init__.py
awarecache/cache.py
awarecache/cache_metrics.py
awarecache/cache_strategies.py
awarecache-1.5.12.dist-info/METADATA
awarecache-1.5.12.dist-info/WHEEL
awarecache-1.5.12.dist-info/top_level.txt
awarecache-1.5.12.dist-info/RECORD
