Metadata-Version: 2.1
Name: awarecache
Version: 1.5.12
Summary: A context-aware caching library with customizable policies and metrics.
Home-page: https://github.com/tobi2x/awarecache
Author: Tobi Ayodeji
Author-email: philayodeji07@gmail.com
Classifier: Development Status :: 3 - Alpha
Classifier: Intended Audience :: Developers
Classifier: License :: OSI Approved :: MIT License
Classifier: Programming Language :: Python :: 3
Classifier: Programming Language :: Python :: 3.8
Classifier: Programming Language :: Python :: 3.9
Classifier: Programming Language :: Python :: 3.10
